insyt/__init__.py
insyt/__main__.py
insyt/analysis.py
insyt/classification.py
insyt/db.py
insyt/file_watcher.py
insyt/inference.py
insyt/ollama.py
insyt/worker.py
insyt/models/__init__.py
insyt/models/ollama/Modelfile
insyt/models/ollama/__init__.py
insyt-0.0.1.dist-info/LICENSE
insyt-0.0.1.dist-info/METADATA
insyt-0.0.1.dist-info/WHEEL
insyt-0.0.1.dist-info/entry_points.txt
insyt-0.0.1.dist-info/top_level.txt
insyt-0.0.1.dist-info/RECORD
