Metadata-Version: 2.1
Name: insyt
Version: 0.0.1
Summary: Innovative Network Security Technologies
Author: Damon Tingey
Author-email: damon.tingey@byu.edu
License: Apache License 2.0
Requires-Python: >=3.10
License-File: LICENSE
Requires-Dist: pandas
Requires-Dist: watchdog
Requires-Dist: tokenizers
Requires-Dist: transformers
Requires-Dist: torch
Requires-Dist: ollama
Requires-Dist: rq
